{
  "posts": [
    {
      "created_time": "2014-05-27 13:37:16", 
      "date": "2014-05-29", 
      "abstract": "生于童年，死于少年。", 
      "author": {
        "id": "1332495", 
        "avatar": "http://img3.douban.com/icon/u1332495-46.jpg", 
        "uid": "A.I.", 
        "url": "http://www.douban.com/people/A.I./", 
        "alt": "细嚼慢咽", 
        "name": "肉腾腾"
      }, 
      "display_style": 10003, 
      "like_count": 270, 
      "id": 101376, 
      "type": "1004", 
      "short_url": "http://dou.bz/3h5aDs", 
      "column": "", 
      "is_liked": false, 
      "thumbs": [
        {
          "id": 100625, 
          "small": {
            "height": 320, 
            "width": 320, 
            "url": "http://img3.douban.com/view/presto/small/public/t100625.jpg"
          }, 
          "description": "", 
          "large": {
            "height": 800, 
            "width": 800, 
            "url": "http://img3.douban.com/view/presto/large/public/t100625.jpg"
          }, 
          "medium": {
            "height": 800, 
            "width": 800, 
            "url": "http://img3.douban.com/view/presto/medium/public/t100625.jpg"
          }, 
          "tag_name": "img_1"
        }, 
        {
          "id": 100626, 
          "small": {
            "height": 481, 
            "width": 320, 
            "url": "http://img3.douban.com/view/presto/small/public/t100626.jpg"
          }, 
          "description": "", 
          "large": {
            "height": 800, 
            "width": 532, 
            "url": "http://img3.douban.com/view/presto/large/public/t100626.jpg"
          }, 
          "medium": {
            "height": 800, 
            "width": 532, 
            "url": "http://img3.douban.com/view/presto/medium/public/t100626.jpg"
          }, 
          "tag_name": "img_2"
        }, 
        {
          "id": 100627, 
          "small": {
            "height": 320, 
            "width": 320, 
            "url": "http://img3.douban.com/view/presto/small/public/t100627.jpg"
          }, 
          "description": "", 
          "large": {
            "height": 800, 
            "width": 800, 
            "url": "http://img3.douban.com/view/presto/large/public/t100627.jpg"
          }, 
          "medium": {
            "height": 800, 
            "width": 800, 
            "url": "http://img3.douban.com/view/presto/medium/public/t100627.jpg"
          }, 
          "tag_name": "img_3"
        }
      ], 
      "published_time": "2014-05-29 21:00:00", 
      "title": "童年时", 
      "original_url": "http://www.douban.com/photos/album/37190006/", 
      "url": "http://moment.douban.com/post/101376/?douban_rec=1"
    }, 
    {
      "created_time": "2014-05-20 11:03:49", 
      "date": "2014-05-29", 
      "abstract": "彭阿姨的朋友是她曾经的同事，做东的是这位同事的丈夫，这位丈夫是慈济大学的一位教授。席间我们相谈甚欢，在教授先生向我介绍了台湾“不能剩饭”的传统之后，我便非常羞涩地将桌上的肉全部吃光了……", 
      "author": {
        "id": "37128232", 
        "avatar": "http://img3.douban.com/icon/u37128232-47.jpg", 
        "uid": "yoko-0423", 
        "url": "http://www.douban.com/people/yoko-0423/", 
        "alt": "", 
        "name": "洋困困"
      }, 
      "display_style": 10001, 
      "like_count": 115, 
      "id": 101134, 
      "type": "1001", 
      "short_url": "http://dou.bz/481COM", 
      "column": "去远方", 
      "is_liked": false, 
      "thumbs": [], 
      "published_time": "2014-05-29 20:00:00", 
      "title": "意想不到的台湾旅行之花莲篇", 
      "original_url": "http://www.douban.com/note/303896549/", 
      "url": "http://moment.douban.com/post/101134/?douban_rec=1"
    }, 
    {
      "created_time": "2014-04-29 15:30:08", 
      "date": "2014-05-29", 
      "abstract": "每个人都要抱着李路哭，想抱他的人太多，有人排不上队，就随便拉个人抱着，嗷嗷地，他们哭成了世界上最恣情且不幸的一屋子。李路觉得自己像是一个婴儿，大哭了一阵子，世界还是同一个样子，他好像做足了一场跟悲痛相关的努力，就暂时释然了。", 
      "author": {
        "id": "1153434", 
        "avatar": "http://img3.douban.com/icon/u1153434-20.jpg", 
        "uid": "nakeddog", 
        "url": "http://www.douban.com/people/nakeddog/", 
        "alt": "", 
        "name": "那可"
      }, 
      "display_style": 10001, 
      "like_count": 118, 
      "id": 100410, 
      "type": "1001", 
      "short_url": "http://dou.bz/0mccIB", 
      "column": "", 
      "is_liked": false, 
      "thumbs": [], 
      "published_time": "2014-05-29 19:00:00", 
      "title": "消失", 
      "original_url": "http://www.douban.com/note/323716981/", 
      "url": "http://moment.douban.com/post/100410/?douban_rec=1"
    }, 
    {
      "created_time": "2014-05-28 16:06:55", 
      "date": "2014-05-29", 
      "abstract": "装逼是一个很大的需求，我认为作为强需求，他完全可以排在“性”前面，列于“食”后面，成为人类第二大强需求。装逼这件事，则同时具备刚性、频度和持续性，终其一生，人们都要装逼。", 
      "author": {
        "id": "2526779", 
        "avatar": "http://img3.douban.com/icon/u2526779-28.jpg", 
        "uid": "tassadar", 
        "url": "http://www.douban.com/people/tassadar/", 
        "alt": "11.01.21-11.10.22.R.I.P", 
        "name": "囧叔"
      }, 
      "display_style": 10001, 
      "like_count": 529, 
      "id": 101419, 
      "type": "1001", 
      "short_url": "http://dou.bz/1oel0N", 
      "column": "", 
      "is_liked": false, 
      "thumbs": [], 
      "published_time": "2014-05-29 17:00:00", 
      "title": "装逼：人类第二强需求", 
      "original_url": "http://www.douban.com/note/354123498/", 
      "url": "http://moment.douban.com/post/101419/?douban_rec=1"
    }, 
    {
      "created_time": "2014-05-28 13:30:09", 
      "date": "2014-05-29", 
      "abstract": "29岁的新加坡女孩Melissa Hie从去年夏天开始，陆续发布了旅途中的“自拍照”，她晒的是当地的美食与美景。之所以会有此灵感，是因为旅途中没有同伴可以代为掌镜。", 
      "author": {
        "id": "69521462", 
        "avatar": "http://img3.douban.com/icon/u69521462-9.jpg", 
        "uid": "69521462", 
        "url": "http://www.douban.com/people/69521462/", 
        "alt": "", 
        "name": "柴犬丸太郎嘻嘻"
      }, 
      "display_style": 10003, 
      "like_count": 440, 
      "id": 101412, 
      "type": "1004", 
      "short_url": "http://dou.bz/0yEGAW", 
      "column": "食记", 
      "is_liked": false, 
      "thumbs": [
        {
          "id": 100620, 
          "small": {
            "height": 320, 
            "width": 320, 
            "url": "http://img3.douban.com/view/presto/small/public/t100620.jpg"
          }, 
          "description": "", 
          "large": {
            "height": 750, 
            "width": 750, 
            "url": "http://img3.douban.com/view/presto/large/public/t100620.jpg"
          }, 
          "medium": {
            "height": 750, 
            "width": 750, 
            "url": "http://img3.douban.com/view/presto/medium/public/t100620.jpg"
          }, 
          "tag_name": "img_1"
        }, 
        {
          "id": 100621, 
          "small": {
            "height": 320, 
            "width": 320, 
            "url": "http://img3.douban.com/view/presto/small/public/t100621.jpg"
          }, 
          "description": "", 
          "large": {
            "height": 750, 
            "width": 750, 
            "url": "http://img3.douban.com/view/presto/large/public/t100621.jpg"
          }, 
          "medium": {
            "height": 750, 
            "width": 750, 
            "url": "http://img3.douban.com/view/presto/medium/public/t100621.jpg"
          }, 
          "tag_name": "img_2"
        }, 
        {
          "id": 100622, 
          "small": {
            "height": 320, 
            "width": 320, 
            "url": "http://img3.douban.com/view/presto/small/public/t100622.jpg"
          }, 
          "description": "", 
          "large": {
            "height": 750, 
            "width": 750, 
            "url": "http://img3.douban.com/view/presto/large/public/t100622.jpg"
          }, 
          "medium": {
            "height": 750, 
            "width": 750, 
            "url": "http://img3.douban.com/view/presto/medium/public/t100622.jpg"
          }, 
          "tag_name": "img_3"
        }
      ], 
      "published_time": "2014-05-29 16:00:00", 
      "title": "吃遍全世界：新加坡女孩的环球街头美食", 
      "original_url": "http://www.douban.com/photos/album/131965116/", 
      "url": "http://moment.douban.com/post/101412/?douban_rec=1"
    }, 
    {
      "created_time": "2014-05-25 15:45:20", 
      "date": "2014-05-29", 
      "abstract": "时间线到底是怎样？教授是怎样复活的？万磁王是怎么恢复能力的？金刚狼的记忆恢复了吗？范冰冰是不是酱油？……", 
      "author": {
        "id": "68255056", 
        "avatar": "http://img3.douban.com/icon/u68255056-2.jpg", 
        "uid": "Abyssssssssss", 
        "url": "http://www.douban.com/people/Abyssssssssss/", 
        "alt": "", 
        "name": "JumpIntoAbyss"
      }, 
      "display_style": 10002, 
      "like_count": 158, 
      "id": 101314, 
      "type": "1003", 
      "short_url": "http://dou.bz/0cyMWY", 
      "column": "看电影", 
      "is_liked": false, 
      "thumbs": [
        {
          "id": 100639, 
          "small": {
            "height": 179, 
            "width": 320, 
            "url": "http://img3.douban.com/view/presto/small/public/t100639.jpg"
          }, 
          "description": "", 
          "large": {
            "height": 337, 
            "width": 600, 
            "url": "http://img3.douban.com/view/presto/large/public/t100639.jpg"
          }, 
          "medium": {
            "height": 337, 
            "width": 600, 
            "url": "http://img3.douban.com/view/presto/medium/public/t100639.jpg"
          }, 
          "tag_name": "img_3"
        }
      ], 
      "published_time": "2014-05-29 15:00:00", 
      "title": "关于《X战警：逆转未来》的全面解读", 
      "original_url": "http://movie.douban.com/review/6678498/", 
      "url": "http://moment.douban.com/post/101314/?douban_rec=1"
    }, 
    {
      "created_time": "2014-05-28 10:57:50", 
      "date": "2014-05-29", 
      "abstract": "首先男人都喜欢美女，我得先好好收拾一下自己的外貌。去剪个齐刘海，买了几套日系OL套装，一瓶香水。一个桃红色的腮红。其次成功男人不喜欢聪明的女人，他们本来在工作中费了脑力，肯定在生活里他们想找个简简单单的另一半……", 
      "author": {
        "id": "33230816", 
        "avatar": "http://img3.douban.com/icon/u33230816-298.jpg", 
        "uid": "ytdb", 
        "url": "http://www.douban.com/people/ytdb/", 
        "alt": "←砍省大美女", 
        "name": "阿菲"
      }, 
      "display_style": 10001, 
      "like_count": 112, 
      "id": 101404, 
      "type": "1001", 
      "short_url": "http://dou.bz/2qeaFD", 
      "column": "哈哈哈", 
      "is_liked": false, 
      "thumbs": [], 
      "published_time": "2014-05-29 12:00:00", 
      "title": "在勾引老板的路上越走越来劲", 
      "original_url": "http://www.douban.com/note/353954338/", 
      "url": "http://moment.douban.com/post/101404/?douban_rec=1"
    }, 
    {
      "created_time": "2014-05-28 10:59:16", 
      "date": "2014-05-29", 
      "abstract": "妙玉，天生成孤癖人皆罕，太高人愈妒，过洁世同嫌。这命必然处女座无疑，自古便被嫌被妒，如今越发被黑得发亮。", 
      "author": {
        "id": "1329080", 
        "avatar": "http://img3.douban.com/icon/u1329080-9.jpg", 
        "uid": "luhua", 
        "url": "http://www.douban.com/people/luhua/", 
        "alt": "灵魂深处有个鬼，这鬼抱住钟馗腿", 
        "name": "芦哲峰"
      }, 
      "display_style": 10002, 
      "like_count": 143, 
      "id": 101406, 
      "type": "1001", 
      "short_url": "http://dou.bz/1mhIql", 
      "column": "", 
      "is_liked": false, 
      "thumbs": [
        {
          "id": 100633, 
          "small": {
            "height": 217, 
            "width": 320, 
            "url": "http://img3.douban.com/view/presto/small/public/t100633.jpg"
          }, 
          "description": "", 
          "large": {
            "height": 408, 
            "width": 600, 
            "url": "http://img3.douban.com/view/presto/large/public/t100633.jpg"
          }, 
          "medium": {
            "height": 408, 
            "width": 600, 
            "url": "http://img3.douban.com/view/presto/medium/public/t100633.jpg"
          }, 
          "tag_name": "img_1"
        }
      ], 
      "published_time": "2014-05-29 11:00:00", 
      "title": "金陵十二钗之星座分析", 
      "original_url": "http://www.douban.com/note/353020923/", 
      "url": "http://moment.douban.com/post/101406/?douban_rec=1"
    }, 
    {
      "created_time": "2014-05-28 10:52:45", 
      "date": "2014-05-29", 
      "abstract": "有人能为我引荐下莫泰168这种酒店的室内设计师吗？我想问问当他们把淋浴间的玻璃窗户就这么对着卧室的时候到底在想什么！", 
      "author": {
        "id": "104495", 
        "avatar": "http://img3.douban.com/view/site/small/public/e5c840d15cc11e3.jpg", 
        "uid": "pairs", 
        "url": "http://site.douban.com/pairs/", 
        "alt": "", 
        "name": "Pairs"
      }, 
      "display_style": 10002, 
      "like_count": 92, 
      "id": 101403, 
      "type": "1001", 
      "short_url": "http://dou.bz/2yqPDZ", 
      "column": "", 
      "is_liked": false, 
      "thumbs": [
        {
          "id": 100637, 
          "small": {
            "height": 320, 
            "width": 320, 
            "url": "http://img3.douban.com/view/presto/small/public/t100637.jpg"
          }, 
          "description": "", 
          "large": {
            "height": 350, 
            "width": 350, 
            "url": "http://img3.douban.com/view/presto/large/public/t100637.jpg"
          }, 
          "medium": {
            "height": 350, 
            "width": 350, 
            "url": "http://img3.douban.com/view/presto/medium/public/t100637.jpg"
          }, 
          "tag_name": "img_1"
        }
      ], 
      "published_time": "2014-05-29 10:00:00", 
      "title": "我在中国玩乐队学习到的东西", 
      "original_url": "http://site.douban.com/pairs/widget/notes/1741981/note/353966620/", 
      "url": "http://moment.douban.com/post/101403/?douban_rec=1"
    }, 
    {
      "created_time": "2014-05-17 19:08:31", 
      "date": "2014-05-29", 
      "abstract": "初夏的风从西边吹来，钻进花丛里不见了踪影。只有少女背带裤脚上沾染的花香，诉说了这场捕风捉影。", 
      "author": {
        "id": "2110697", 
        "avatar": "http://img3.douban.com/icon/u2110697-86.jpg", 
        "uid": "chaoself", 
        "url": "http://www.douban.com/people/chaoself/", 
        "alt": "", 
        "name": "低"
      }, 
      "display_style": 10003, 
      "like_count": 322, 
      "id": 101070, 
      "type": "1004", 
      "short_url": "http://dou.bz/3bmNKP", 
      "column": "", 
      "is_liked": false, 
      "thumbs": [
        {
          "id": 100628, 
          "small": {
            "height": 320, 
            "width": 320, 
            "url": "http://img3.douban.com/view/presto/small/public/t100628.jpg"
          }, 
          "description": "", 
          "large": {
            "height": 900, 
            "width": 900, 
            "url": "http://img3.douban.com/view/presto/large/public/t100628.jpg"
          }, 
          "medium": {
            "height": 900, 
            "width": 900, 
            "url": "http://img3.douban.com/view/presto/medium/public/t100628.jpg"
          }, 
          "tag_name": "img_1"
        }, 
        {
          "id": 100629, 
          "small": {
            "height": 320, 
            "width": 320, 
            "url": "http://img3.douban.com/view/presto/small/public/t100629.jpg"
          }, 
          "description": "", 
          "large": {
            "height": 900, 
            "width": 900, 
            "url": "http://img3.douban.com/view/presto/large/public/t100629.jpg"
          }, 
          "medium": {
            "height": 900, 
            "width": 900, 
            "url": "http://img3.douban.com/view/presto/medium/public/t100629.jpg"
          }, 
          "tag_name": "img_2"
        }, 
        {
          "id": 100630, 
          "small": {
            "height": 320, 
            "width": 320, 
            "url": "http://img3.douban.com/view/presto/small/public/t100630.jpg"
          }, 
          "description": "", 
          "large": {
            "height": 900, 
            "width": 900, 
            "url": "http://img3.douban.com/view/presto/large/public/t100630.jpg"
          }, 
          "medium": {
            "height": 900, 
            "width": 900, 
            "url": "http://img3.douban.com/view/presto/medium/public/t100630.jpg"
          }, 
          "tag_name": "img_3"
        }
      ], 
      "published_time": "2014-05-29 09:00:00", 
      "title": "捕风の彼女", 
      "original_url": "http://www.douban.com/photos/album/131397475/", 
      "url": "http://moment.douban.com/post/101070/?douban_rec=1"
    }, 
    {
      "created_time": "2014-05-28 14:34:13", 
      "date": "2014-05-29", 
      "abstract": "健身搭档是非常重要的，主要功能是保护人身安全。次要功能是在组间的时候来计算休息时间。最次要功能是用来在训练过程中吹牛逼。", 
      "author": {
        "id": "3601685", 
        "avatar": "http://img3.douban.com/icon/u3601685-8.jpg", 
        "uid": "myrror", 
        "url": "http://www.douban.com/people/myrror/", 
        "alt": "无私帮助别人才能证明我还活着！", 
        "name": "西门镜湖"
      }, 
      "display_style": 10002, 
      "like_count": 226, 
      "id": 101417, 
      "type": "1002", 
      "short_url": "http://dou.bz/2sqftd", 
      "column": "爱美丽", 
      "is_liked": false, 
      "thumbs": [
        {
          "id": 100624, 
          "small": {
            "height": 212, 
            "width": 320, 
            "url": "http://img3.douban.com/view/presto/small/public/t100624.jpg"
          }, 
          "description": "", 
          "large": {
            "height": 332, 
            "width": 500, 
            "url": "http://img3.douban.com/view/presto/large/public/t100624.jpg"
          }, 
          "medium": {
            "height": 332, 
            "width": 500, 
            "url": "http://img3.douban.com/view/presto/medium/public/t100624.jpg"
          }, 
          "tag_name": "img_1"
        }
      ], 
      "published_time": "2014-05-29 08:00:00", 
      "title": "如何勾搭一个你专属的健身搭档", 
      "original_url": "http://www.douban.com/group/topic/53297113/", 
      "url": "http://moment.douban.com/post/101417/?douban_rec=1"
    }, 
    {
      "created_time": "2014-05-28 14:17:01", 
      "date": "2014-05-29", 
      "abstract": "丘瞎子老早就在江湖上绝迹了，但是他的传说却从未消停。所有人说起他来语气都寒飕飕的，感觉就像玩篮球的人说起上古大神张伯伦。丘瞎子既然能够轻轻松松背贴着城墙游上去，轻功肯定是绝顶的了，而论起内功据说连汤山老道都未必是他的对手。", 
      "author": {
        "id": "", 
        "avatar": "", 
        "uid": "", 
        "url": "http://read.douban.com/author/63694855", 
        "alt": "", 
        "name": "屠音鞘"
      }, 
      "display_style": 10001, 
      "like_count": 67, 
      "id": 101414, 
      "type": "1007", 
      "short_url": "http://dou.bz/0F8tS3", 
      "column": "", 
      "is_liked": false, 
      "thumbs": [], 
      "published_time": "2014-05-29 04:00:00", 
      "title": "其实不瞎的丘瞎子", 
      "original_url": "http://read.douban.com/column/673195/chapter/3910006/", 
      "url": "http://moment.douban.com/post/101414/?douban_rec=1"
    }, 
    {
      "created_time": "2014-05-16 12:29:10", 
      "date": "2014-05-29", 
      "abstract": "小说选择了大时代里的小人物作为主体，教读者看见时代的陶轮被打翻在地之后，个人的命运是何等颠沛流离，曲折离奇。", 
      "author": {
        "id": "1035632", 
        "avatar": "http://img3.douban.com/icon/u1035632-7.jpg", 
        "uid": "hecaitou", 
        "url": "http://www.douban.com/people/hecaitou/", 
        "alt": "", 
        "name": "和菜头"
      }, 
      "display_style": 10002, 
      "like_count": 122, 
      "id": 101016, 
      "type": "1003", 
      "short_url": "http://dou.bz/1HlnNI", 
      "column": "闲翻书", 
      "is_liked": false, 
      "thumbs": [
        {
          "id": 100623, 
          "small": {
            "height": 320, 
            "width": 320, 
            "url": "http://img3.douban.com/view/presto/small/public/t100623.jpg"
          }, 
          "description": "", 
          "large": {
            "height": 800, 
            "width": 800, 
            "url": "http://img3.douban.com/view/presto/large/public/t100623.jpg"
          }, 
          "medium": {
            "height": 800, 
            "width": 800, 
            "url": "http://img3.douban.com/view/presto/medium/public/t100623.jpg"
          }, 
          "tag_name": "img_1"
        }
      ], 
      "published_time": "2014-05-29 04:00:00", 
      "title": "为了赶时髦而读书是可耻的", 
      "original_url": "http://book.douban.com/review/6669915/", 
      "url": "http://moment.douban.com/post/101016/?douban_rec=1"
    }, 
    {
      "created_time": "2014-05-25 16:49:42", 
      "date": "2014-05-29", 
      "abstract": "少室山下，斜阳古道，一个梳双髻的青衣女子骑着毛驴慢慢走过，毛驴的脚步惊飞了一树归鸦……", 
      "author": {
        "id": "45074177", 
        "avatar": "http://img3.douban.com/icon/u45074177-2.jpg", 
        "uid": "45074177", 
        "url": "http://www.douban.com/people/45074177/", 
        "alt": "到这儿来找小伙伴", 
        "name": "慕容素衣"
      }, 
      "display_style": 10002, 
      "like_count": 211, 
      "id": 101323, 
      "type": "1001", 
      "short_url": "http://dou.bz/38SxgR", 
      "column": "", 
      "is_liked": false, 
      "thumbs": [
        {
          "id": 100631, 
          "small": {
            "height": 481, 
            "width": 320, 
            "url": "http://img3.douban.com/view/presto/small/public/t100631.jpg"
          }, 
          "description": "", 
          "large": {
            "height": 600, 
            "width": 399, 
            "url": "http://img3.douban.com/view/presto/large/public/t100631.jpg"
          }, 
          "medium": {
            "height": 600, 
            "width": 399, 
            "url": "http://img3.douban.com/view/presto/medium/public/t100631.jpg"
          }, 
          "tag_name": "img_1"
        }
      ], 
      "published_time": "2014-05-29 00:00:00", 
      "title": "你所不知道的金庸另一面", 
      "original_url": "http://www.douban.com/note/313614574/", 
      "url": "http://moment.douban.com/post/101323/?douban_rec=1"
    }, 
    {
      "created_time": "2014-05-12 10:26:25", 
      "date": "2014-05-29", 
      "abstract": "她就端上了一盘碧绿碧绿的，闪着油花的青菜，一点辣椒都没放，只点缀着几粒拍碎了的跟白玉一样的蒜籽，那是我平日里最爱吃的。我莫名地就觉得喉咙里被什么给堵住了似的，想要说点什么，张开了嘴唇却是半点声音也发不出。", 
      "author": {
        "id": "24111692", 
        "avatar": "http://img3.douban.com/icon/u24111692-15.jpg", 
        "uid": "linulaoyao", 
        "url": "http://www.douban.com/people/linulaoyao/", 
        "alt": "我要锻炼身体！我要练出马甲线！", 
        "name": "狸奴三公子"
      }, 
      "display_style": 10001, 
      "like_count": 157, 
      "id": 100871, 
      "type": "1001", 
      "short_url": "http://dou.bz/3nnLMF", 
      "column": "", 
      "is_liked": false, 
      "thumbs": [], 
      "published_time": "2014-05-29 00:00:00", 
      "title": "一碗没有辣椒的炒青菜", 
      "original_url": "http://www.douban.com/note/350346309/", 
      "url": "http://moment.douban.com/post/100871/?douban_rec=1"
    }, 
    {
      "created_time": "2014-05-12 18:04:32", 
      "date": "2014-05-29", 
      "abstract": "来德国之后在外上厕所一直是我的心头病。从小在共产主义花园里快乐成长的我被贪婪的资本主义分分钟吓哭，上个洗手间居然要一欧，一欧是什么概念你造嘛？！你造嘛？！一升牛奶才8毛钱，为了把它排泄出去，我居然要花1欧！", 
      "author": {
        "id": "3602846", 
        "avatar": "http://img3.douban.com/icon/u3602846-213.jpg", 
        "uid": "ikausume", 
        "url": "http://www.douban.com/people/ikausume/", 
        "alt": "←真人和头像一样高冷", 
        "name": "宇宙高冷小乌贼"
      }, 
      "display_style": 10001, 
      "like_count": 289, 
      "id": 100884, 
      "type": "1001", 
      "short_url": "http://dou.bz/12Wn4d", 
      "column": "生活在别处", 
      "is_liked": false, 
      "thumbs": [], 
      "published_time": "2014-05-29 00:00:00", 
      "title": "你在德国这么二，你家人知道么", 
      "original_url": "http://www.douban.com/note/320386262/", 
      "url": "http://moment.douban.com/post/100884/?douban_rec=1"
    }
  ], 
  "date": "2014-05-29", 
  "total": 16
}